CHANGELOG.txt
LICENCE.txt
README.md
setup.py
keepActive/__init__.py
keepActive/keepActive.py
keepActive.egg-info/PKG-INFO
keepActive.egg-info/SOURCES.txt
keepActive.egg-info/dependency_links.txt
keepActive.egg-info/requires.txt
keepActive.egg-info/top_level.txt