Metadata-Version: 2.1
Name: keepActive
Version: 0.0.1
Summary: Keeps the computer active
Author: art_bat
Author-email: art_bat0@icloud.com
Keywords: idle,python,active
Classifier: Development Status :: 4 - Beta
Classifier: Intended Audience :: End Users/Desktop
Classifier: License :: OSI Approved :: MIT License
Classifier: Programming Language :: Python :: 3
Classifier: Operating System :: MacOS :: MacOS X
Classifier: Operating System :: Microsoft :: Windows
License-File: LICENCE.txt
